{"diagrams":[
{"id":"fig-m07-overview","visualQuestionId":"q-m07-overview","question":"Hogyan változtatsz biztonságosan egy ismeretlen viselkedésű rendszeren?","type":"relationship","disposition":"page-local","rendering":"inline-svg","diagramType":"relationship-map","takeaway":"Az oldal célja, fő összefüggései és elvárt résztvevői eredménye egyetlen térképen látható.","glossarySlugs":["safety-net","characterization-test","legacy-system","seam","strangler-pattern","rollback"],"figureSelector":"#fig-m07-overview","svgSelector":"#fig-m07-overview svg","textFallbackSelector":"#fig-m07-overview-text","inlineSvgHash":"44fb0676dc43715b3747b64ad57abf7be2dd65516dec8979defc78c1dcd81861"},
{"id":"fig-m07-mi-a-kulonbseg-a-vedtelen","visualQuestionId":"q-m07-relationship-1","question":"Mi a különbség a védtelen és a védőhálós változtatás között?","type":"relationship","disposition":"page-local","rendering":"inline-svg","diagramType":"relationship-map","takeaway":"A kapcsolatok megmutatják, mely elemek erősítik vagy korlátozzák egymást.","glossarySlugs":["safety-net"],"figureSelector":"#fig-m07-mi-a-kulonbseg-a-vedtelen","svgSelector":"#fig-m07-mi-a-kulonbseg-a-vedtelen svg","textFallbackSelector":"#fig-m07-mi-a-kulonbseg-a-vedtelen-text","inlineSvgHash":"474e3abeaad173ca3af8a126fb21d1fd4d72f50c1a3ac759ea46fa04137ed347"},
{"id":"fig-m07-hogyan-rogzited-a-megfigyelt-viselkedest","visualQuestionId":"q-m07-process-2","question":"Hogyan rögzíted a megfigyelt viselkedést characterization teszttel?","type":"process","disposition":"page-local","rendering":"inline-svg","diagramType":"flowchart","takeaway":"A lépések sorrendje és az átadási pontok együtt teszik követhetővé a folyamatot.","glossarySlugs":["characterization-test","legacy-system"],"figureSelector":"#fig-m07-hogyan-rogzited-a-megfigyelt-viselkedest","svgSelector":"#fig-m07-hogyan-rogzited-a-megfigyelt-viselkedest svg","textFallbackSelector":"#fig-m07-hogyan-rogzited-a-megfigyelt-viselkedest-text","inlineSvgHash":"7ede22579d89126d70eb3f452f79aeb675118d05828c8ff5f8d6a46bb5d04992"},
{"id":"fig-m07-hol-a-cserepont-a-komponensek","visualQuestionId":"q-m07-structure-3","question":"Hol a cserepont a komponensek között?","type":"structure","disposition":"page-local","rendering":"inline-svg","diagramType":"component-diagram","takeaway":"Az elemek határai és függőségei határozzák meg a működő egészet.","glossarySlugs":["seam","strangler-pattern"],"figureSelector":"#fig-m07-hol-a-cserepont-a-komponensek","svgSelector":"#fig-m07-hol-a-cserepont-a-komponensek svg","textFallbackSelector":"#fig-m07-hol-a-cserepont-a-komponensek-text","inlineSvgHash":"5d6bfda918167512f68d5682a9948ac535454e86864fa9d2aec1b147beda3e10"},
{"id":"fig-m07-mikor-bovitesz-mikor-allsz-meg","visualQuestionId":"q-m07-decision-4","question":"Mikor bővítesz, mikor állsz meg, és hogyan lépsz vissza?","type":"decision","disposition":"page-local","rendering":"inline-svg","diagramType":"decision-tree","takeaway":"A választást a bemeneti feltételek és a következő ellenőrzési pont vezérli.","glossarySlugs":["rollback"],"figureSelector":"#fig-m07-mikor-bovitesz-mikor-allsz-meg","svgSelector":"#fig-m07-mikor-bovitesz-mikor-allsz-meg svg","textFallbackSelector":"#fig-m07-mikor-bovitesz-mikor-allsz-meg-text","inlineSvgHash":"ec967d23cfffea2b1f8c3c4e4835106656c4d2060933df0b4ef62a19486c8203"}
]}
